osrm/__init__.py
osrm/core.py
osrm/extra.py
osrm-0.11.3.dist-info/LICENSE
osrm-0.11.3.dist-info/METADATA
osrm-0.11.3.dist-info/WHEEL
osrm-0.11.3.dist-info/top_level.txt
osrm-0.11.3.dist-info/RECORD
