Metadata-Version: 2.1
Name: osrm
Version: 0.11.3
Summary: A Python wrapper around the OSRM API
Home-page: https://github.com/ustroetz/python-osrm
Author: Ulric Stroetz, mthh
Author-email: ustroetz@gmail.com
License: UNKNOWN
Platform: UNKNOWN
Requires-Dist: polyline
Requires-Dist: GDAL
Requires-Dist: numpy
Requires-Dist: pandas
Requires-Dist: shapely
Requires-Dist: geopandas
Requires-Dist: matplotlib
